{"user_name":"Artur Mulagalijev","user_username":"amulagalijev","user_bio":"Integrations specialist with deep expertise in sales data pipelines, B2B workflows, and API integrations. I design production-ready n8n templates that turn complex data operations into seamless, hands-off processes.","user_links":"https://www.youtube.com/@Coresignal","user_avatar":"https://gravatar.com/avatar/fe8f55c18149ef4f7b17f2c454e8f7bd0cd50a4b2a03bd047e4ca345c692a649?r=pg&d=retro&size=200","url":"https://n8nworkflows.xyz/workflows/identify-company-decision-makers-with-coresignal-and-google-sheets-16415\n","url_n8n":"https://n8n.io/workflows/16415","nodeTypes":{"n8n-nodes-base.if":{"count":2},"n8n-nodes-base.code":{"count":1},"n8n-nodes-base.stickyNote":{"count":6},"n8n-nodes-base.googleSheets":{"count":2},"n8n-nodes-base.manualTrigger":{"count":1},"n8n-nodes-base.splitInBatches":{"count":1},"n8n-nodes-coresignal-api.coresignal":{"count":6}},"categories":[{"id":37,"name":"Lead Generation"}]}