{"user_name":"Patrick Graham","user_username":"pgraham","user_bio":"PMP · CCMP · MBA · Lean Six Sigma Green Belt\nProject manager with experience across construction, enterprise software rollout, procurement, and facility buildouts.\nI build practical n8n automation tools for project managers — execution briefs, vendor coordination, and workflow automation that reduces manual follow-through.\npmexecution.com","user_links":"www.pmexecution.com","user_avatar":"https://gravatar.com/avatar/748a2dee604a1e7524f15d05b57b38da274416182688a8506b5872cd222ec1a3?r=pg&d=retro&size=200","url":"https://n8nworkflows.xyz/workflows/capture-vendor-status-updates-via-tokenized-email-links-and-google-sheets-15982\n","url_n8n":"https://n8n.io/workflows/15982","nodeTypes":{"n8n-nodes-base.if":{"count":1},"n8n-nodes-base.code":{"count":6},"n8n-nodes-base.filter":{"count":1},"n8n-nodes-base.webhook":{"count":1},"n8n-nodes-base.emailSend":{"count":1},"n8n-nodes-base.stickyNote":{"count":3},"n8n-nodes-base.googleSheets":{"count":4},"n8n-nodes-base.scheduleTrigger":{"count":1},"n8n-nodes-base.respondToWebhook":{"count":2}},"categories":[{"id":46,"name":"Project Management"}]}