{"user_name":"Gainium","user_username":"aressanch","user_bio":"","user_links":"https://gainium.io/","user_avatar":"https://gravatar.com/avatar/6b9f08b97e0b6fddb3e8bc848bca1866a09defecaa87f6e53688f18fb37706b6?r=pg&d=retro&size=200","url":"https://n8nworkflows.xyz/workflows/deploy-gainium-dca-bot-pairs-with-telegram-approval-and-google-sheets-logging-16764\n","url_n8n":"https://n8n.io/workflows/16764","nodeTypes":{"n8n-nodes-base.if":{"count":1},"n8n-nodes-base.set":{"count":1},"n8n-nodes-base.code":{"count":1},"n8n-nodes-base.telegram":{"count":5},"n8n-nodes-base.stickyNote":{"count":6},"n8n-nodes-gainium.Gainium":{"count":3},"n8n-nodes-base.errorTrigger":{"count":1},"n8n-nodes-base.googleSheets":{"count":1},"n8n-nodes-base.scheduleTrigger":{"count":1}},"categories":[{"id":44,"name":"Crypto Trading"}]}